[
  {
    "repository": "eggjs/egg",
    "ref": "next",
    "path": "eggjs/egg",
    "command": "oxfmt"
  },
  {
    "repository": "actualbudget/actual",
    "ref": "master",
    "path": "actual",
    "command": "oxfmt"
  },
  {
    "repository": "AmanVarshney01/create-better-t-stack",
    "ref": "main",
    "path": "AmanVarshney01/create-better-t-stack",
    "command": "oxfmt"
  },
  {
    "repository": "cnpm/cnpmcore",
    "ref": "master",
    "path": "cnpmcore",
    "command": "oxfmt"
  },
  {
    "repository": "monkeytypegame/monkeytype",
    "ref": "master",
    "path": "monkeytype",
    "command": "oxfmt"
  },
  {
    "repository": "formatjs/formatjs",
    "ref": "main",
    "path": "formatjs",
    "command": "oxfmt"
  },
  {
    "repository": "vuejs/core",
    "ref": "minor",
    "path": "vue",
    "command": "oxfmt"
  },
  {
    "repository": "fuma-nama/fumadocs",
    "ref": "dev",
    "path": "fumadocs",
    "command": "oxfmt"
  },
  {
    "repository": "fastify/fastify-vite",
    "ref": "main",
    "path": "fastify-vite",
    "command": "oxfmt"
  }
]